aise/__init__.py
aise/aise.py
aise/dataset/__init__.py
aise/dataset/base.py
aise/dataset/data/fixations.csv
aise/dataset/data/phm_RIGHT_RPhase_FB.csv
aise/model/__init__.py
aise/preprocess/__init__.py
aise/validate/__init__.py
aise/visualize/__init__.py
aise/visualize/base.py
aise-0.1.4.dist-info/LICENSE
aise-0.1.4.dist-info/METADATA
aise-0.1.4.dist-info/WHEEL
aise-0.1.4.dist-info/top_level.txt
aise-0.1.4.dist-info/RECORD
